{
  "project_info": {
    "project_number": "1054457270326",
    "project_id": "flash-chat-46153",
    "storage_bucket": "flash-chat-46153.appspot.com"
  },
  "client": [
    {
      "client_info": {
        "mobilesdk_app_id": "1:1054457270326:android:38e03788734badcbff4897",
        "android_client_info": {
          "package_name": "com.NikhilMalusare.flash_chat"
        }
      },
      "oauth_client": [
        {
          "client_id": "1054457270326-ngiu4jchiavum43vs2684nd4ja1jj1pp.apps.googleusercontent.com",
          "client_type": 3
        }
      ],
      "api_key": [
        {
          "current_key": "AIzaSyD6qtURQ0VPlyF5P6SYGLxgwRL2XmEmoPk"
        }
      ],
      "services": {
        "appinvite_service": {
          "other_platform_oauth_client": [
            {
              "client_id": "1054457270326-ngiu4jchiavum43vs2684nd4ja1jj1pp.apps.googleusercontent.com",
              "client_type": 3
            }
          ]
        }
      }
    }
  ],
  "configuration_version": "1"
}